setup.py
createurls/__init__.py
createurls.egg-info/PKG-INFO
createurls.egg-info/SOURCES.txt
createurls.egg-info/dependency_links.txt
createurls.egg-info/entry_points.txt
createurls.egg-info/requires.txt
createurls.egg-info/top_level.txt