Metadata-Version: 1.0
Name: createurls
Version: 0.0.1
Summary: Create urls suited for jmeter tests from apache logs
Home-page: https://github.com/tback/createurls
Author: Till Backhaus
Author-email: till@backha.us
License: MIT
Platform: UNKNOWN
